energy_tracker_core/__init__.py
energy_tracker_core/cli.py
energy_tracker_core/py.typed
energy_tracker_core/GlobalConfig/__init__.py
energy_tracker_core/GlobalConfig/config_reader.py
energy_tracker_core/GlobalConfig/globals.py
energy_tracker_core/HardwareTracker/__init__.py
energy_tracker_core/HardwareTracker/test.py
energy_tracker_core/HardwareTracker/AsyncService/__init__.py
energy_tracker_core/HardwareTracker/AsyncService/async_server.py
energy_tracker_core/HardwareTracker/AsyncService/client.py
energy_tracker_core/HardwareTracker/CommandLineInterface/__init__.py
energy_tracker_core/HardwareTracker/CommandLineInterface/command_line_interface.py
energy_tracker_core/HardwareTracker/Tracker/__init__.py
energy_tracker_core/HardwareTracker/Tracker/csv_handler.py
energy_tracker_core/HardwareTracker/Tracker/power_monitor.py
energy_tracker_core/HardwareTracker/Tracker/tracker.py
energy_tracker_core/Visulization/app.py
energy_tracker_core/Visulization/test.py
energy_tracker_core/Visulization/workspace_task.py
energy_tracker_core/Visulization/pages/1_welcome.py
energy_tracker_core/Visulization/pages/2_csv管理.py
energy_tracker_core/Visulization/pages/3_绘图展板.py
energy_tracker_core/Visulization/pages/4_结果对比.py
energy_tracker_core/config/config.json
energy_tracker_core/config/doc.txt
energy_tracker_core/data/.keep
energy_tracker_core-0.5.0.dist-info/METADATA
energy_tracker_core-0.5.0.dist-info/WHEEL
energy_tracker_core-0.5.0.dist-info/entry_points.txt
energy_tracker_core-0.5.0.dist-info/licenses/LICENSE
energy_tracker_core-0.5.0.dist-info/RECORD
