Metadata-Version: 2.4
Name: energy-tracker-core
Version: 0.5.0
Summary: A cpu and gpu energy tracker based on the LibreHardwareMonitor and NVML.
Author-email: philippe <philippe.qu@outlook.com>
License-File: LICENSE
Requires-Python: >=3.13
Requires-Dist: aiohttp>=3.11.18
Requires-Dist: click>=8.2.0
Requires-Dist: pydantic>=2.11.4
Requires-Dist: pynvml>=12.0.0
Requires-Dist: rich>=14.0.0
Requires-Dist: scipy>=1.15.3
Requires-Dist: streamlit>=1.45.1
Requires-Dist: wmi>=1.5.1
